{
  "name" : "Project",
  "originTableName" : "project",
  "comment" : null,
  "fullColumn" : [ {
    "name" : "id",
    "comment" : null,
    "type" : null,
    "shortType" : null,
    "ktShortType" : "Int",
    "custom" : false,
    "ext" : { }
  }, {
    "name" : "groupId",
    "comment" : null,
    "type" : null,
    "shortType" : null,
    "ktShortType" : "Int",
    "custom" : false,
    "ext" : { }
  }, {
    "name" : "name",
    "comment" : null,
    "type" : null,
    "shortType" : null,
    "ktShortType" : "String",
    "custom" : false,
    "ext" : { }
  }, {
    "name" : "desc",
    "comment" : null,
    "type" : null,
    "shortType" : null,
    "ktShortType" : "String",
    "custom" : false,
    "ext" : { }
  }, {
    "name" : "updateTime",
    "comment" : null,
    "type" : null,
    "shortType" : null,
    "ktShortType" : "LocalDateTime",
    "custom" : false,
    "ext" : { }
  }, {
    "name" : "createTime",
    "comment" : null,
    "type" : null,
    "shortType" : null,
    "ktShortType" : "LocalDateTime",
    "custom" : false,
    "ext" : { }
  } ],
  "pkColumn" : null,
  "otherColumn" : null,
  "savePackageName" : "com.theone.tools.waterfall",
  "savePath" : "/Users/chenxiaotong/Work/tools/waterfall/src/main/java/com/theone/tools/waterfall",
  "saveModelName" : "waterfall"
}